---
layout: post
title: dis模块与python 底层实现
categories: python
tags:
- python底层
---

自从接触gevent后，对python代码的一些底层实现产生了兴趣，刚好发现了dis模块，可以讲python的函数编译为字节码，这样就可以简单的了解python的技术内幕了。

主要通过dis模块分析了一下两点

1. swap函数的实现

swap函数按照pythonic的风格定义，应该使用swap1,而不是下面的swap2，并且很多地方都提到过，swap1的性能要比swap2好，这里用dis看一下两个函数的字节码有什么区别
{% highlight python %}
def swap1():
    a = 1
    b = 2
    a,b=b,a
    
def swap2():
    a = 1
    b = 2
    tmp = a
    a = b
    b = tmp
{% endhighlight %}

    >>> dis.dis(swap1)
    2           0 LOAD_CONST               1 (1)
                3 STORE_FAST               0 (a)

    3           6 LOAD_CONST               2 (2)
                9 STORE_FAST               1 (b)

    4          12 LOAD_FAST                1 (b)
               15 LOAD_FAST                0 (a)
               18 ROT_TWO             
               19 STORE_FAST               0 (a)
               22 STORE_FAST               1 (b)
               25 LOAD_CONST               0 (None)
               28 RETURN_VALUE        
             
    >>> dis.dis(swap2)
    2           0 LOAD_CONST               1 (1)
                3 STORE_FAST               0 (a)

    3           6 LOAD_CONST               2 (2)
                9 STORE_FAST               1 (b)

    4          12 LOAD_FAST                0 (a)
               15 STORE_FAST               2 (tmp)

    5          18 LOAD_FAST                1 (b)
               21 STORE_FAST               0 (a)

    6          24 LOAD_FAST                2 (tmp)
               27 STORE_FAST               1 (b)
               30 LOAD_CONST               0 (None)
               33 RETURN_VALUE        
               
这里我们发现，除去两句初始化语句，swap1是7行字节码，swap2是8行字节码，这就体现出了性能区别

ROT_TWO按文档定义是交换函数栈顶的两个元素，
要比一句LOADFAST再加STORE_FAST节省时间

这就是swap1比swap2效率高的原因所在，通过timeit比较一下两者的运行时间，则一切了然
    >>> Timer(swap1).timeit()
    0.8129569198974606
    >>> Timer(swap2).timeit()
    0.8650318511451704

2. yield的实现

yield其实可以算作是一种编程方式，gevent的底层运用很多，虽然并不是一种先进的编程技术，但对于我来说，也是接触python之后才开始了解这种编程模式。

yield简单的说，就是函数遇到yield之后，将yield的操作数返回，再次调用函数的时候，从yield的下一句开始执行，一直执行到yield再次返回。

我在这里简单的实现了一个斐波那契数列函数

{% highlight python %}
def fb():
    a,b = 0,1
	while True:
		yield a
		a,b = b,a+b
{% endhighlight %}

其对应的字节码如下

    >>> dis.dis(fb)
    2           0 LOAD_CONST               3 ((0, 1))
                3 UNPACK_SEQUENCE          2
                6 STORE_FAST               0 (a)
                9 STORE_FAST               1 (b)

    3          12 SETUP_LOOP              32 (to 47)
          >>   15 LOAD_GLOBAL              0 (True)
               18 POP_JUMP_IF_FALSE       46

    4          21 LOAD_FAST                0 (a)
               24 YIELD_VALUE         
               25 POP_TOP             

    5          26 LOAD_FAST                1 (b)
               29 LOAD_FAST                0 (a)
               32 LOAD_FAST                1 (b)
               35 BINARY_ADD          
               36 ROT_TWO             
               37 STORE_FAST               0 (a)
               40 STORE_FAST               1 (b)
               43 JUMP_ABSOLUTE           15
          >>   46 POP_BLOCK           
          >>   47 LOAD_CONST               0 (None)
               50 RETURN_VALUE        
               
看完这段字节码，其实就是一些简单的循环和跳转，YIELD_VALUE是yield的一句实现，并没有显示出太多实现细节，对python字节码进行解释执行的代码在./Python下 名字为ceval.c

其中有一段处理返回值的代码如下

{% highlight c %}
#ifdef CASE_TOO_BIG
        default: switch (opcode) {
#endif
        case RAISE_VARARGS:
            u = v = w = NULL;
            switch (oparg) {
            case 3:
                u = POP(); /* traceback */
                /* Fallthrough */
            case 2:
                v = POP(); /* value */
                /* Fallthrough */
            case 1:
                w = POP(); /* exc */
            case 0: /* Fallthrough */
                why = do_raise(w, v, u);
                break;
            default:
                PyErr_SetString(PyExc_SystemError,
                           "bad RAISE_VARARGS oparg");
                why = WHY_EXCEPTION;
                break;
            }
            break;

        case LOAD_LOCALS:
            if ((x = f->f_locals) != NULL) {
                Py_INCREF(x);
                PUSH(x);
                continue;
            }
            PyErr_SetString(PyExc_SystemError, "no locals");
            break;

        case RETURN_VALUE:
            retval = POP();
            why = WHY_RETURN;
            goto fast_block_end;

        case YIELD_VALUE:
            retval = POP();
            f->f_stacktop = stack_pointer;
            why = WHY_YIELD;
            goto fast_yield;

        case EXEC_STMT:
            w = TOP();
            v = SECOND();
            u = THIRD();
            STACKADJ(-3);
            READ_TIMESTAMP(intr0);
            err = exec_statement(f, u, v, w);
            READ_TIMESTAMP(intr1);
            Py_DECREF(u);
            Py_DECREF(v);
            Py_DECREF(w);
            break;
{% endhighlight %}

这里，我们尅看到对应YIELD_VALUE字节码的解析代码是如下几句：

{% highlight c %}
case YIELD_VALUE:
            retval = POP();
            f->f_stacktop = stack_pointer;
            why = WHY_YIELD;
            goto fast_yield;
{% endhighlight%}

简单的分析，首先弹出返回值，然后把当前栈指针保存，标记为YIELD，跳转到fast_yield

fast_yield部分的代码主要是一些异常处理，


代码中，关于WHY_YIELD有这样一段定义

{% highlight c %}
/* Status code for main loop (reason for stack unwind) */
enum why_code {
        WHY_NOT =       0x0001, /* No error */
        WHY_EXCEPTION = 0x0002, /* Exception occurred */
        WHY_RERAISE =   0x0004, /* Exception re-raised by 'finally' */
        WHY_RETURN =    0x0008, /* 'return' statement */
        WHY_BREAK =     0x0010, /* 'break' statement */
        WHY_CONTINUE =  0x0020, /* 'continue' statement */
        WHY_YIELD =     0x0040  /* 'yield' operator */
};
{% endhighlight %}

这里WHU_YIELD和WHYRETURN都是主函数的一个状态值这里说明，YIELD和RETURN是函数的一个状态，通过一个指针保存YIELD函数的栈顶，下次从YIELD下一句开始执行，并利用当前函数栈现场，即可实现YIELD的功能。


以上是对yield的一个简单分析，日后还需要深入挖掘。


通过dis模块和python的源代码阅读，可以很好的深入理解python实现原理，对写出高质量的python代码有很大的帮助。